prettyjson/__init__.py
prettyjson/__main__.py
prettyjson/tool.py
prettyjson-1.0.3.dist-info/LICENSE
prettyjson-1.0.3.dist-info/METADATA
prettyjson-1.0.3.dist-info/WHEEL
prettyjson-1.0.3.dist-info/top_level.txt
prettyjson-1.0.3.dist-info/RECORD
