Metadata-Version: 2.1
Name: prettyjson
Version: 1.0.3
Summary: Command-line tool to validate and pretty-print JSON(just for the missing options in `json.tool`)
Home-page: https://github.com/vimfunny/prettyjson
Author: vimfun
Author-email: vimfunny@gmail.com
License: PSF license
Platform: UNKNOWN
Classifier: Development Status :: 5 - Production/Stable
Classifier: License :: OSI Approved :: MIT License
Classifier: Intended Audience :: Developers
Classifier: Intended Audience :: System Administrators
Classifier: Environment :: Console
Classifier: Operating System :: OS Independent
Classifier: Programming Language :: Python
Classifier: Programming Language :: Python :: 3
Classifier: Programming Language :: Python :: 3.4
Classifier: Programming Language :: Python :: 3.5
Classifier: Programming Language :: Python :: 3.6
Classifier: Programming Language :: Python :: 3.7
Classifier: Programming Language :: Python :: 3.8
Classifier: Programming Language :: Python :: 3 :: Only
Classifier: Topic :: System :: Shells
Classifier: Topic :: Text Processing
Classifier: Topic :: Text Processing :: Filters
